python_llm_factory/__init__.py
python_llm_factory/llm_factory.py
python_llm_factory/config/__init__.py
python_llm_factory/config/anthropic_settings.py
python_llm_factory/config/base_settings.py
python_llm_factory/config/gemini_settings.py
python_llm_factory/config/llama_settings.py
python_llm_factory/config/open_ai_settings.py
python_llm_factory/config/settings.py
python_llm_factory/consts/__init__.py
python_llm_factory/consts/provider.py
python_llm_factory/hooks/__init__.py
python_llm_factory/hooks/error_hooks.py
python_llm_factory/hooks/logging_hooks.py
python_llm_factory/tools/__init__.py
python_llm_factory-0.0.5.dist-info/licenses/LICENSE
python_llm_factory-0.0.5.dist-info/METADATA
python_llm_factory-0.0.5.dist-info/WHEEL
python_llm_factory-0.0.5.dist-info/entry_points.txt
python_llm_factory-0.0.5.dist-info/top_level.txt
python_llm_factory-0.0.5.dist-info/RECORD
