Metadata-Version: 2.4
Name: python-llm-factory
Version: 0.0.5
Summary: A flexible Python factory for working with multiple Large Language Model (LLM) providers (OpenAI, Anthropic, Gemini, Llama) using a unified interface, with robust configuration and extensibility.
Home-page: https://github.com/aviz92/python-llm-factory
Author: Avi Zaguri
Author-email: 
Project-URL: Repository, https://github.com/aviz92/python-llm-factory
Classifier: Framework :: Pytest
Classifier: Programming Language :: Python
Requires-Python: >=3.11
License-File: LICENSE
Requires-Dist: setuptools
Requires-Dist: wheel
Requires-Dist: python-dotenv
Requires-Dist: pre-commit
Requires-Dist: colorlog
Requires-Dist: pytest
Requires-Dist: pathlib
Requires-Dist: PyYAML
Requires-Dist: pydantic
Requires-Dist: pydantic-settings
Requires-Dist: openai
Requires-Dist: anthropic
Requires-Dist: google-genai
Requires-Dist: instructor
Requires-Dist: instructor[anthropic]
Requires-Dist: instructor[google-genai]
Requires-Dist: custom-python-logger
Requires-Dist: pytest-plugins
Dynamic: author
Dynamic: classifier
Dynamic: description
Dynamic: description-content-type
Dynamic: home-page
Dynamic: license-file
Dynamic: project-url
Dynamic: requires-dist
Dynamic: requires-python
Dynamic: summary
